marcia/__init__.py
marcia/mask.py
marcia-0.1.6.dist-info/LICENSE
marcia-0.1.6.dist-info/METADATA
marcia-0.1.6.dist-info/WHEEL
marcia-0.1.6.dist-info/top_level.txt
marcia-0.1.6.dist-info/RECORD
