Metadata-Version: 2.1
Name: marcia
Version: 0.1.6
Summary: Manual hyperspectral data classifier
Author-email: Hadrien Meyer <meyerhadrien96@gmail.com>
License: GNU GENERAL PUBLIC LICENSE
Project-URL: Homepage, https://github.com/hameye/marcia
Project-URL: Example, https://github.com/hameye/MARCIA/blob/master/examples/Tutorial.ipynb
Project-URL: Source, https://github.com/hameye/MARCIA
Project-URL: Report a bug, https://github.com/hameye/MARCIA/issues
Classifier: License :: OSI Approved :: GNU General Public License v3 (GPLv3)
Classifier: Operating System :: OS Independent
Classifier: Programming Language :: Python :: 3.7
Classifier: Typing :: Typed
Requires-Python: >=3.7
License-File: LICENSE
